README.md
Readme.md
buildno
requirements.txt
setup.py
windnet/__init__.py
windnet/dnsresolv.py
windnet/iproute.py
windnet/iptables.py
windnet/iptools.py
windnet/testudp.py
windnet.egg-info/PKG-INFO
windnet.egg-info/SOURCES.txt
windnet.egg-info/dependency_links.txt
windnet.egg-info/entry_points.txt
windnet.egg-info/requires.txt
windnet.egg-info/top_level.txt