Metadata-Version: 2.1
Name: windnet
Version: 2.1.0.22
Summary: windnet
Home-page: http://www.bing.com
Author: heguofeng
Author-email: heguofeng@189.cn
License: UNKNOWN
Keywords: windnet
Platform: UNKNOWN
Classifier: Development Status :: 3 - Alpha
Classifier: Intended Audience :: Developers
Classifier: Topic :: Internet
Classifier: License :: OSI Approved :: MIT License
Classifier: Programming Language :: Python :: 3
Classifier: Programming Language :: Python :: 3.3
Classifier: Programming Language :: Python :: 3.4
Classifier: Programming Language :: Python :: 3.5
Requires-Python: >3
